pypergraph/__init__.py
pypergraph/_constants.py
pypergraph/_core.py
pypergraph/_tools.py
pypergraph/_typing.py
pypergraph-0.0.1.dist-info/LICENSE
pypergraph-0.0.1.dist-info/WHEEL
pypergraph-0.0.1.dist-info/METADATA
pypergraph-0.0.1.dist-info/RECORD
