Metadata-Version: 2.1
Name: pypergraph
Version: 0.0.1
Summary: Hypergraph data structure in Python.
Keywords: hypergraph,datastructure
Author: Xavier Lin
Requires-Python: >=3.7
Classifier: License :: OSI Approved :: MIT License
Classifier: Programming Language :: Python :: 3.7
Classifier: Programming Language :: Python :: 3.8
Classifier: Programming Language :: Python :: 3.9
Classifier: Programming Language :: Python :: 3.10
Requires-Dist: typing_extensions; python_version<'3.8'
Requires-Dist: black ; extra == "dev"
Requires-Dist: flake8 ; extra == "dev"
Requires-Dist: flake8-docstrings ; extra == "dev"
Requires-Dist: flit ; extra == "dev"
Requires-Dist: isort ; extra == "dev"
Requires-Dist: mypy ; extra == "dev"
Requires-Dist: nox ; extra == "dev"
Requires-Dist: furo ; extra == "doc"
Requires-Dist: myst-parser ; extra == "doc"
Requires-Dist: sphinx ; extra == "doc"
Requires-Dist: flake8 ; extra == "qa"
Requires-Dist: flake8-docstrings ; extra == "qa"
Requires-Dist: mypy ; extra == "qa"
Requires-Dist: pytest ; extra == "test"
Requires-Dist: pytest-cov ; extra == "test"
Project-URL: documentation, https://pypergraph.readthedocs.io/
Project-URL: source, https://codeberg.org/meadow/pypergraph
Provides-Extra: dev
Provides-Extra: doc
Provides-Extra: qa
Provides-Extra: test
